gallop/__init__.py
gallop/call.py
gallop/classroom.py
gallop/config.py
gallop/funcs.py
gallop/bin/gallop
gallop-0.0.6.data/scripts/gallop
gallop-0.0.6.dist-info/LICENSE
gallop-0.0.6.dist-info/METADATA
gallop-0.0.6.dist-info/WHEEL
gallop-0.0.6.dist-info/top_level.txt
gallop-0.0.6.dist-info/RECORD
