Metadata-Version: 2.1
Name: gallop
Version: 0.0.6
Home-page: https://github.com/raynardj/gallop
License: GPLv3+
Project-URL: Documentation, https://github.com/raynardj/gallop
Project-URL: Tracker, https://github.com/raynardj/gallop/issues
Classifier: Development Status :: 3 - Alpha
Classifier: Intended Audience :: End Users/Desktop
Classifier: License :: OSI Approved :: GNU General Public License v3 (GPLv3)
Classifier: Natural Language :: English
Classifier: Programming Language :: Python :: 3.6
Classifier: Programming Language :: Python :: 3.7
Classifier: Programming Language :: Python :: 3.8
Classifier: Programming Language :: Python :: 3.9
Classifier: Programming Language :: Python :: 3.10
Requires-Python: >=3.6
License-File: LICENSE
Requires-Dist: pyyaml
Requires-Dist: fire (>=0.4.0)
Requires-Dist: regex
